{
  "shifts": [
    [
      {
        "day": 0,
        "hour": 0,
        "onyens": []
      },
      {
        "day": 0,
        "hour": 1,
        "onyens": []
      },
      {
        "day": 0,
        "hour": 2,
        "onyens": []
      },
      {
        "day": 0,
        "hour": 3,
        "onyens": []
      },
      {
        "day": 0,
        "hour": 4,
        "onyens": []
      },
      {
        "day": 0,
        "hour": 5,
        "onyens": []
      },
      {
        "day": 0,
        "hour": 6,
        "onyens": []
      },
      {
        "day": 0,
        "hour": 7,
        "onyens": []
      },
      {
        "day": 0,
        "hour": 8,
        "onyens": []
      },
      {
        "day": 0,
        "hour": 9,
        "onyens": []
      },
      {
        "day": 0,
        "hour": 10,
        "onyens": []
      },
      {
        "day": 0,
        "hour": 11,
        "onyens": []
      },
      {
        "day": 0,
        "hour": 12,
        "onyens": [
          "cclarkm",
          "ltrogdon",
          "kgbuige",
          "youngjt"
        ]
      },
      {
        "day": 0,
        "hour": 13,
        "onyens": [
          "marygold",
          "cclarkm",
          "ltrogdon",
          "kgbuige",
          "youngjt"
        ]
      },
      {
        "day": 0,
        "hour": 14,
        "onyens": [
          "julialp",
          "marygold",
          "masonmc",
          "rrd",
          "kgbuige"
        ]
      },
      {
        "day": 0,
        "hour": 15,
        "onyens": [
          "marygold",
          "morgana4",
          "ruiwu",
          "justbea"
        ]
      },
      {
        "day": 0,
        "hour": 16,
        "onyens": [
          "marygold",
          "ruiwu",
          "justbea",
          "masonmc",
          "zakl14"
        ]
      },
      {
        "day": 0,
        "hour": 17,
        "onyens": []
      },
      {
        "day": 0,
        "hour": 18,
        "onyens": []
      },
      {
        "day": 0,
        "hour": 19,
        "onyens": []
      },
      {
        "day": 0,
        "hour": 20,
        "onyens": []
      },
      {
        "day": 0,
        "hour": 21,
        "onyens": []
      },
      {
        "day": 0,
        "hour": 22,
        "onyens": []
      },
      {
        "day": 0,
        "hour": 23,
        "onyens": []
      }
    ],
    [
      {
        "day": 1,
        "hour": 0,
        "onyens": []
      },
      {
        "day": 1,
        "hour": 1,
        "onyens": []
      },
      {
        "day": 1,
        "hour": 2,
        "onyens": []
      },
      {
        "day": 1,
        "hour": 3,
        "onyens": []
      },
      {
        "day": 1,
        "hour": 4,
        "onyens": []
      },
      {
        "day": 1,
        "hour": 5,
        "onyens": []
      },
      {
        "day": 1,
        "hour": 6,
        "onyens": []
      },
      {
        "day": 1,
        "hour": 7,
        "onyens": []
      },
      {
        "day": 1,
        "hour": 8,
        "onyens": []
      },
      {
        "day": 1,
        "hour": 9,
        "onyens": []
      },
      {
        "day": 1,
        "hour": 10,
        "onyens": [
          "justindo",
          "dfirrin",
          "tiaram",
          "zakl14",
          "hdezwaan"
        ]
      },
      {
        "day": 1,
        "hour": 11,
        "onyens": [
          "zihe",
          "kyracm",
          "julialp",
          "tiaram"
        ]
      },
      {
        "day": 1,
        "hour": 12,
        "onyens": [
          "zihe",
          "julialp",
          "reshea",
          "mpetruzz",
          "markp"
        ]
      },
      {
        "day": 1,
        "hour": 13,
        "onyens": [
          "jamhenry",
          "mpetruzz",
          "krissy",
          "cole15s",
          "brookebc",
          "zakl14"
        ]
      },
      {
        "day": 1,
        "hour": 14,
        "onyens": [
          "brookebc",
          "chrisdis",
          "zakl14",
          "dunnac11"
        ]
      },
      {
        "day": 1,
        "hour": 15,
        "onyens": [
          "johnjo8",
          "justbea",
          "brookebc",
          "hdezwaan",
          "dunnac11"
        ]
      },
      {
        "day": 1,
        "hour": 16,
        "onyens": [
          "johnjo8",
          "brookebc",
          "wberner",
          "chrisdis",
          "hdezwaan",
          "eheckel"
        ]
      },
      {
        "day": 1,
        "hour": 17,
        "onyens": [
          "morgana4",
          "perryh",
          "johnjo8",
          "ssneha",
          "wberner",
          "eheckel"
        ]
      },
      {
        "day": 1,
        "hour": 18,
        "onyens": [
          "morgana4",
          "perryh",
          "ssneha",
          "guerrera",
          "eheckel"
        ]
      },
      {
        "day": 1,
        "hour": 19,
        "onyens": [
          "morgana4",
          "perryh",
          "mpetruzz",
          "nlaurenr",
          "hubermm",
          "eheckel"
        ]
      },
      {
        "day": 1,
        "hour": 20,
        "onyens": []
      },
      {
        "day": 1,
        "hour": 21,
        "onyens": []
      },
      {
        "day": 1,
        "hour": 22,
        "onyens": []
      },
      {
        "day": 1,
        "hour": 23,
        "onyens": []
      }
    ],
    [
      {
        "day": 2,
        "hour": 0,
        "onyens": []
      },
      {
        "day": 2,
        "hour": 1,
        "onyens": []
      },
      {
        "day": 2,
        "hour": 2,
        "onyens": []
      },
      {
        "day": 2,
        "hour": 3,
        "onyens": []
      },
      {
        "day": 2,
        "hour": 4,
        "onyens": []
      },
      {
        "day": 2,
        "hour": 5,
        "onyens": []
      },
      {
        "day": 2,
        "hour": 6,
        "onyens": []
      },
      {
        "day": 2,
        "hour": 7,
        "onyens": []
      },
      {
        "day": 2,
        "hour": 8,
        "onyens": []
      },
      {
        "day": 2,
        "hour": 9,
        "onyens": []
      },
      {
        "day": 2,
        "hour": 10,
        "onyens": [
          "justindo",
          "krissy",
          "brooksmt",
          "zakl14",
          "heather1"
        ]
      },
      {
        "day": 2,
        "hour": 11,
        "onyens": [
          "justindo",
          "perryh",
          "benl1",
          "krissy",
          "brooksmt",
          "zakl14",
          "guerrera",
          "heather1"
        ]
      },
      {
        "day": 2,
        "hour": 12,
        "onyens": [
          "sydneycs",
          "benl1",
          "krissy",
          "wberner",
          "zakl14"
        ]
      },
      {
        "day": 2,
        "hour": 13,
        "onyens": [
          "rasikar",
          "sydneycs",
          "masonmc",
          "krissy",
          "ltrogdon"
        ]
      },
      {
        "day": 2,
        "hour": 14,
        "onyens": [
          "kateg",
          "justindo",
          "zihe",
          "sirine",
          "smganci",
          "brooksmt",
          "vemm97"
        ]
      },
      {
        "day": 2,
        "hour": 15,
        "onyens": [
          "kateg",
          "smganci",
          "brookebc",
          "vemm97"
        ]
      },
      {
        "day": 2,
        "hour": 16,
        "onyens": [
          "kateg",
          "krislenn",
          "masonmc",
          "smganci",
          "chrisdis",
          "vemm97"
        ]
      },
      {
        "day": 2,
        "hour": 17,
        "onyens": [
          "kakiryan",
          "armandoj",
          "krislenn",
          "sirine",
          "ltrogdon",
          "smganci",
          "shanesp",
          "chrisdis"
        ]
      },
      {
        "day": 2,
        "hour": 18,
        "onyens": [
          "armandoj",
          "ruiwu",
          "mpetruzz",
          "rrd",
          "ltrogdon",
          "wberner",
          "guerrera"
        ]
      },
      {
        "day": 2,
        "hour": 19,
        "onyens": [
          "armandoj",
          "ruiwu",
          "mpetruzz",
          "hubermm",
          "rrd",
          "wberner",
          "guerrera"
        ]
      },
      {
        "day": 2,
        "hour": 20,
        "onyens": []
      },
      {
        "day": 2,
        "hour": 21,
        "onyens": []
      },
      {
        "day": 2,
        "hour": 22,
        "onyens": []
      },
      {
        "day": 2,
        "hour": 23,
        "onyens": []
      }
    ],
    [
      {
        "day": 3,
        "hour": 0,
        "onyens": []
      },
      {
        "day": 3,
        "hour": 1,
        "onyens": []
      },
      {
        "day": 3,
        "hour": 2,
        "onyens": []
      },
      {
        "day": 3,
        "hour": 3,
        "onyens": []
      },
      {
        "day": 3,
        "hour": 4,
        "onyens": []
      },
      {
        "day": 3,
        "hour": 5,
        "onyens": []
      },
      {
        "day": 3,
        "hour": 6,
        "onyens": []
      },
      {
        "day": 3,
        "hour": 7,
        "onyens": []
      },
      {
        "day": 3,
        "hour": 8,
        "onyens": []
      },
      {
        "day": 3,
        "hour": 9,
        "onyens": []
      },
      {
        "day": 3,
        "hour": 10,
        "onyens": [
          "julialp",
          "tabathav",
          "perryh",
          "tiaram",
          "guerrera"
        ]
      },
      {
        "day": 3,
        "hour": 11,
        "onyens": [
          "kyracm",
          "julialp",
          "tiaram"
        ]
      },
      {
        "day": 3,
        "hour": 12,
        "onyens": [
          "kyracm",
          "reshea"
        ]
      },
      {
        "day": 3,
        "hour": 13,
        "onyens": [
          "kyracm",
          "reshea",
          "jamhenry",
          "eaa",
          "dfirrin",
          "fiordali"
        ]
      },
      {
        "day": 3,
        "hour": 14,
        "onyens": [
          "reshea",
          "jamhenry",
          "eaa",
          "ssneha",
          "dfirrin"
        ]
      },
      {
        "day": 3,
        "hour": 15,
        "onyens": [
          "reshea",
          "jamhenry",
          "ssneha",
          "fiordali"
        ]
      },
      {
        "day": 3,
        "hour": 16,
        "onyens": [
          "armandoj",
          "tabathav",
          "ssneha",
          "jgalfaro",
          "wberner",
          "guerrera"
        ]
      },
      {
        "day": 3,
        "hour": 17,
        "onyens": [
          "rasikar",
          "tabathav",
          "perryh",
          "jgalfaro",
          "tiaram",
          "wberner",
          "guerrera"
        ]
      },
      {
        "day": 3,
        "hour": 18,
        "onyens": [
          "rasikar",
          "tabathav",
          "rrd",
          "wberner",
          "guerrera"
        ]
      },
      {
        "day": 3,
        "hour": 19,
        "onyens": [
          "ruiwu",
          "nlaurenr",
          "rrd",
          "wberner"
        ]
      },
      {
        "day": 3,
        "hour": 20,
        "onyens": []
      },
      {
        "day": 3,
        "hour": 21,
        "onyens": []
      },
      {
        "day": 3,
        "hour": 22,
        "onyens": []
      },
      {
        "day": 3,
        "hour": 23,
        "onyens": []
      }
    ],
    [
      {
        "day": 4,
        "hour": 0,
        "onyens": []
      },
      {
        "day": 4,
        "hour": 1,
        "onyens": []
      },
      {
        "day": 4,
        "hour": 2,
        "onyens": []
      },
      {
        "day": 4,
        "hour": 3,
        "onyens": []
      },
      {
        "day": 4,
        "hour": 4,
        "onyens": []
      },
      {
        "day": 4,
        "hour": 5,
        "onyens": []
      },
      {
        "day": 4,
        "hour": 6,
        "onyens": []
      },
      {
        "day": 4,
        "hour": 7,
        "onyens": []
      },
      {
        "day": 4,
        "hour": 8,
        "onyens": []
      },
      {
        "day": 4,
        "hour": 9,
        "onyens": []
      },
      {
        "day": 4,
        "hour": 10,
        "onyens": [
          "justindo",
          "perryh",
          "brooksmt",
          "zakl14",
          "heather1"
        ]
      },
      {
        "day": 4,
        "hour": 11,
        "onyens": [
          "justindo",
          "lydialyd",
          "perryh",
          "zakl14",
          "heather1"
        ]
      },
      {
        "day": 4,
        "hour": 12,
        "onyens": [
          "lydialyd",
          "ghstein",
          "shanesp",
          "zakl14"
        ]
      },
      {
        "day": 4,
        "hour": 13,
        "onyens": [
          "ghstein",
          "ltrogdon",
          "cole15s",
          "shanesp"
        ]
      },
      {
        "day": 4,
        "hour": 14,
        "onyens": [
          "kateg",
          "kyracm",
          "jamhenry",
          "vemm97"
        ]
      },
      {
        "day": 4,
        "hour": 15,
        "onyens": [
          "kateg",
          "ihinks",
          "vemm97",
          "sydneyam"
        ]
      },
      {
        "day": 4,
        "hour": 16,
        "onyens": [
          "kateg",
          "krislenn",
          "justbea",
          "markp",
          "jgalfaro",
          "ihinks",
          "sydneyam"
        ]
      },
      {
        "day": 4,
        "hour": 17,
        "onyens": [
          "krislenn",
          "cclarkm",
          "justbea",
          "markp",
          "jgalfaro",
          "kgbuige",
          "shanesp"
        ]
      },
      {
        "day": 4,
        "hour": 18,
        "onyens": [
          "krislenn",
          "sydneycs",
          "cclarkm",
          "kgbuige",
          "shanesp",
          "guerrera"
        ]
      },
      {
        "day": 4,
        "hour": 19,
        "onyens": [
          "krislenn",
          "cclarkm",
          "benl1",
          "kgbuige",
          "shanesp",
          "guerrera"
        ]
      },
      {
        "day": 4,
        "hour": 20,
        "onyens": []
      },
      {
        "day": 4,
        "hour": 21,
        "onyens": []
      },
      {
        "day": 4,
        "hour": 22,
        "onyens": []
      },
      {
        "day": 4,
        "hour": 23,
        "onyens": []
      }
    ],
    [
      {
        "day": 5,
        "hour": 0,
        "onyens": []
      },
      {
        "day": 5,
        "hour": 1,
        "onyens": []
      },
      {
        "day": 5,
        "hour": 2,
        "onyens": []
      },
      {
        "day": 5,
        "hour": 3,
        "onyens": []
      },
      {
        "day": 5,
        "hour": 4,
        "onyens": []
      },
      {
        "day": 5,
        "hour": 5,
        "onyens": []
      },
      {
        "day": 5,
        "hour": 6,
        "onyens": []
      },
      {
        "day": 5,
        "hour": 7,
        "onyens": []
      },
      {
        "day": 5,
        "hour": 8,
        "onyens": []
      },
      {
        "day": 5,
        "hour": 9,
        "onyens": []
      },
      {
        "day": 5,
        "hour": 10,
        "onyens": []
      },
      {
        "day": 5,
        "hour": 11,
        "onyens": [
          "cara97"
        ]
      },
      {
        "day": 5,
        "hour": 12,
        "onyens": [
          "cara97"
        ]
      },
      {
        "day": 5,
        "hour": 13,
        "onyens": [
          "cara97"
        ]
      },
      {
        "day": 5,
        "hour": 14,
        "onyens": [
          "cara97",
          "brooksmt"
        ]
      },
      {
        "day": 5,
        "hour": 15,
        "onyens": []
      },
      {
        "day": 5,
        "hour": 16,
        "onyens": []
      },
      {
        "day": 5,
        "hour": 17,
        "onyens": []
      },
      {
        "day": 5,
        "hour": 18,
        "onyens": []
      },
      {
        "day": 5,
        "hour": 19,
        "onyens": []
      },
      {
        "day": 5,
        "hour": 20,
        "onyens": []
      },
      {
        "day": 5,
        "hour": 21,
        "onyens": []
      },
      {
        "day": 5,
        "hour": 22,
        "onyens": []
      },
      {
        "day": 5,
        "hour": 23,
        "onyens": []
      }
    ],
    [
      {
        "day": 6,
        "hour": 0,
        "onyens": []
      },
      {
        "day": 6,
        "hour": 1,
        "onyens": []
      },
      {
        "day": 6,
        "hour": 2,
        "onyens": []
      },
      {
        "day": 6,
        "hour": 3,
        "onyens": []
      },
      {
        "day": 6,
        "hour": 4,
        "onyens": []
      },
      {
        "day": 6,
        "hour": 5,
        "onyens": []
      },
      {
        "day": 6,
        "hour": 6,
        "onyens": []
      },
      {
        "day": 6,
        "hour": 7,
        "onyens": []
      },
      {
        "day": 6,
        "hour": 8,
        "onyens": []
      },
      {
        "day": 6,
        "hour": 9,
        "onyens": []
      },
      {
        "day": 6,
        "hour": 10,
        "onyens": []
      },
      {
        "day": 6,
        "hour": 11,
        "onyens": []
      },
      {
        "day": 6,
        "hour": 12,
        "onyens": []
      },
      {
        "day": 6,
        "hour": 13,
        "onyens": []
      },
      {
        "day": 6,
        "hour": 14,
        "onyens": []
      },
      {
        "day": 6,
        "hour": 15,
        "onyens": []
      },
      {
        "day": 6,
        "hour": 16,
        "onyens": []
      },
      {
        "day": 6,
        "hour": 17,
        "onyens": []
      },
      {
        "day": 6,
        "hour": 18,
        "onyens": []
      },
      {
        "day": 6,
        "hour": 19,
        "onyens": []
      },
      {
        "day": 6,
        "hour": 20,
        "onyens": []
      },
      {
        "day": 6,
        "hour": 21,
        "onyens": []
      },
      {
        "day": 6,
        "hour": 22,
        "onyens": []
      },
      {
        "day": 6,
        "hour": 23,
        "onyens": []
      }
    ]
  ]
}